sidll.so
sidll-0.17.dist-info/RECORD
sidll-0.17.dist-info/WHEEL
sidll-0.17.dist-info/METADATA
