Metadata-Version: 2.2
Name: sidll
Version: 0.17
Summary: Sparse Indexed Doubly Linked List
Author-Email: John Goh <jkh.goh@gmail.com>
License: MIT
Classifier: Programming Language :: Python :: 3
Classifier: License :: OSI Approved :: MIT License
Classifier: Operating System :: OS Independent
Classifier: Development Status :: 3 - Alpha
Requires-Python: >=3.9
